[
    {
        "model": "aluno.turma",
        "pk": 1,
        "fields": {
            "turma_nome": "1º Período - Educação Infantil",
            "turma_ano": 2023,
            "turma_periodo": "Tarde"
        }
    },
    {
        "model": "aluno.turma",
        "pk": 2,
        "fields": {
            "turma_nome": "2º Período - Educação Infantil",
            "turma_ano": 2023,
            "turma_periodo": "Tarde"
        }
    },
    {
        "model": "aluno.turma",
        "pk": 3,
        "fields": {
            "turma_nome": "1º Ano - Ensino Fundamental",
            "turma_ano": 2023,
            "turma_periodo": "Tarde"
        }
    },
    {
        "model": "aluno.turma",
        "pk": 4,
        "fields": {
            "turma_nome": "2º Ano - Ensino Fundamental",
            "turma_ano": 2023,
            "turma_periodo": "Tarde"
        }
    },
    {
        "model": "aluno.turma",
        "pk": 5,
        "fields": {
            "turma_nome": "3º Ano - Ensino Fundamental",
            "turma_ano": 2023,
            "turma_periodo": "Tarde"
        }
    },
    {
        "model": "aluno.turma",
        "pk": 6,
        "fields": {
            "turma_nome": "4º Ano - Ensino Fundamental",
            "turma_ano": 2023,
            "turma_periodo": "Tarde"
        }
    },
    {
        "model": "aluno.turma",
        "pk": 7,
        "fields": {
            "turma_nome": "5º Ano - Ensino Fundamental",
            "turma_ano": 2023,
            "turma_periodo": "Tarde"
        }
    },
    {
        "model": "aluno.turma",
        "pk": 8,
        "fields": {
            "turma_nome": "6º Ano - Ensino Fundamental",
            "turma_ano": 2023,
            "turma_periodo": "Manhã"
        }
    },
    {
        "model": "aluno.turma",
        "pk": 9,
        "fields": {
            "turma_nome": "7º Ano - Ensino Fundamental",
            "turma_ano": 2023,
            "turma_periodo": "Manhã"
        }
    },
    {
        "model": "aluno.turma",
        "pk": 10,
        "fields": {
            "turma_nome": "8º Ano - Ensino Fundamental",
            "turma_ano": 2023,
            "turma_periodo": "Manhã"
        }
    },
    {
        "model": "aluno.turma",
        "pk": 11,
        "fields": {
            "turma_nome": "9º Ano - Ensino Fundamental",
            "turma_ano": 2023,
            "turma_periodo": "Manhã"
        }
    },

    {
        "model": "aluno.turma",
        "pk": 12,
        "fields": {
            "turma_nome": "1º Ano - Ensino Médio",
            "turma_ano": 2023,
            "turma_periodo": "Noite"
        }
    },
    {
        "model": "aluno.turma",
        "pk": 13,
        "fields": {
            "turma_nome": "2º Ano - Ensino Médio",
            "turma_ano": 2023,
            "turma_periodo": "Noite"
        }
    },
    {
        "model": "aluno.turma",
        "pk": 14,
        "fields": {
            "turma_nome": "3º Ano - Ensino Médio",
            "turma_ano": 2023,
            "turma_periodo": "Noite"
        }
    }

]

